Metadata-Version: 2.1
Name: plasTeX
Version: 3.1
Summary: LaTeX document processing framework
Home-page: http://plastex.github.io/plastex/
Author: Kevin D. Smith
Author-email: Kevin.Smith@sas.com
Classifier: Programming Language :: Python :: 3
Classifier: License :: OSI Approved :: MIT License
Classifier: Operating System :: OS Independent
Requires-Python: >=3.6
License-File: LICENSE
Requires-Dist: Jinja2>=2.10.1
Requires-Dist: Unidecode>=0.4.21
Requires-Dist: Pillow>=7
Requires-Dist: typing-extensions>=3.7
